{
    "shoulder_pan": {
        "id": 1,
        "drive_mode": 0,
        "homing_offset": -1658,
        "range_min": 796,
        "range_max": 3272
    },
    "shoulder_lift": {
        "id": 2,
        "drive_mode": 0,
        "homing_offset": 730,
        "range_min": 819,
        "range_max": 3243
    },
    "elbow_flex": {
        "id": 3,
        "drive_mode": 0,
        "homing_offset": 1149,
        "range_min": 945,
        "range_max": 3171
    },
    "wrist_flex": {
        "id": 4,
        "drive_mode": 0,
        "homing_offset": -1487,
        "range_min": 790,
        "range_max": 3197
    },
    "wrist_roll": {
        "id": 5,
        "drive_mode": 0,
        "homing_offset": 487,
        "range_min": 0,
        "range_max": 4095
    },
    "gripper": {
        "id": 6,
        "drive_mode": 0,
        "homing_offset": 1494,
        "range_min": 2034,
        "range_max": 3278
    }
}